CONTRIBUTING.md
LICENSE
MANIFEST.in
README.rst
requirements-dev.txt
requirements.txt
setup.py
coursera/__init__.py
coursera/api.py
coursera/cookies.py
coursera/coursera_dl.py
coursera/credentials.py
coursera/define.py
coursera/downloaders.py
coursera/network.py
coursera/utils.py
coursera.egg-info/PKG-INFO
coursera.egg-info/SOURCES.txt
coursera.egg-info/dependency_links.txt
coursera.egg-info/entry_points.txt
coursera.egg-info/requires.txt
coursera.egg-info/top_level.txt